dforge/__init__.py
dforge/core.py
dforge/plotData.py
dforge-2.1.5.dist-info/LICENSE
dforge-2.1.5.dist-info/METADATA
dforge-2.1.5.dist-info/WHEEL
dforge-2.1.5.dist-info/top_level.txt
dforge-2.1.5.dist-info/RECORD
