Metadata-Version: 2.1
Name: dforge
Version: 2.1.5
Summary: A package for efortless data manager.
Home-page: https://github.com/LuizaRusnac/dforge.git
Author: Luiza Rusnac
Author-email: luiza.rusnac93@gmail.com
Classifier: Development Status :: 3 - Alpha
Classifier: Programming Language :: Python :: 3
Classifier: License :: OSI Approved :: MIT License
Classifier: Operating System :: OS Independent
Requires-Python: >=3.6
License-File: LICENSE
Requires-Dist: matplotlib
Requires-Dist: numpy
Requires-Dist: pandas
Requires-Dist: scikit-learn
Requires-Dist: tabulate
